bstk_notitia/__init__.py
bstk_notitia/error.py
bstk_notitia/lib/abc/driver.py
bstk_notitia/lib/abc/informant.py
bstk_notitia/lib/abc/investigator.py
bstk_notitia/lib/abc/observer.py
bstk_notitia/lib/abc/reporter.py
bstk_notitia/loader.py
bstk_notitia/modules/driver/mongodb.py
bstk_notitia/modules/driver/null.py
bstk_notitia/modules/driver/passthrough.py
bstk_notitia/modules/informant/internal/datetime.py
bstk_notitia/modules/informant/internal/http.py
bstk_notitia/modules/investigator/internal/clock.py
bstk_notitia/modules/investigator/internal/mongo_record_processor.py
bstk_notitia/modules/investigator/internal/notitia_casereporter.py
bstk_notitia/modules/observer/internal/mongo_changestream.py
bstk_notitia/modules/observer/internal/mongo_collectionstream.py
bstk_notitia/modules/observer/internal/mongo_record.py
bstk_notitia/modules/observer/internal/tick.py
bstk_notitia/modules/reporter/internal/echo.py
bstk_notitia/modules/reporter/internal/mongo_record.py
bstk_notitia/modules/reporter/internal/notitia_case.py
bstk_notitia/notitia.py
bstk_notitia/roster.py
bstk_notitia-0.6.6.dist-info/METADATA
bstk_notitia-0.6.6.dist-info/WHEEL
bstk_notitia-0.6.6.dist-info/RECORD
