Metadata-Version: 2.1
Name: bstk_notitia
Version: 0.6.6
Summary: notitia core runtime & modules
Author: colin
Author-email: colin@broadstack.com.au
Requires-Python: >=3.11,<4.0
Classifier: Programming Language :: Python :: 3
Classifier: Programming Language :: Python :: 3.11
Classifier: Programming Language :: Python :: 3.12
Requires-Dist: dateparser (>=1.2.0,<2.0.0)
Requires-Dist: motor (>=3.3.2,<4.0.0)
Requires-Dist: python-dotenv[cli] (>=1.0.0,<2.0.0)
Requires-Dist: simplejson (>=3.19.2,<4.0.0)
Requires-Dist: timedelta-isoformat (>=0.6.2.11,<0.7.0.0)
